mapstery/__init__.py
mapstery/filter.py
mapstery/map.py
mapstery-0.0.7.dist-info/LICENSE
mapstery-0.0.7.dist-info/METADATA
mapstery-0.0.7.dist-info/WHEEL
mapstery-0.0.7.dist-info/top_level.txt
mapstery-0.0.7.dist-info/RECORD
