Metadata-Version: 2.1
Name: mapstery
Version: 0.0.7
Summary: Digital terrain map manipulation high level functions
Home-page: https://gitlab.com/frontierdevelopmentlab/space-resources/mapstery
Author: Red Boumghar
License: BSD
Keywords: GDAL,python,raster,dataset,multilayer,multichannel,layers,channels,gis,information
Platform: UNKNOWN
Classifier: Development Status :: 3 - Alpha
Classifier: Intended Audience :: Developers
Classifier: Programming Language :: Python :: 3
Classifier: License :: OSI Approved :: BSD License
Requires-Python: >=3
Requires-Dist: gdal
Requires-Dist: Pillow
Requires-Dist: scipy
Requires-Dist: numpy
Provides-Extra: test
Requires-Dist: pytest ; extra == 'test'
Requires-Dist: pytest-cov ; extra == 'test'
